{"OpenedDocuments":"[{\"DocumentPath\":\"Main.xaml\",\"FactoryId\":\"{ACB8E7BA-F093-44C1-9B50-33ECA51AAE16}\"},{\"DocumentPath\":\"Sim.xaml\",\"FactoryId\":\"{ACB8E7BA-F093-44C1-9B50-33ECA51AAE16}\"},{\"DocumentPath\":\"Dispatcher.xaml\",\"FactoryId\":\"{ACB8E7BA-F093-44C1-9B50-33ECA51AAE16}\"},{\"DocumentPath\":\"Buoi5.xaml\",\"FactoryId\":\"{ACB8E7BA-F093-44C1-9B50-33ECA51AAE16}\"},{\"DocumentPath\":\"Buoi7.xaml\",\"FactoryId\":\"{ACB8E7BA-F093-44C1-9B50-33ECA51AAE16}\"},{\"DocumentPath\":\"Buoi2.xaml\",\"FactoryId\":\"{ACB8E7BA-F093-44C1-9B50-33ECA51AAE16}\"},{\"DocumentPath\":\"Buoi3.xaml\",\"FactoryId\":\"{ACB8E7BA-F093-44C1-9B50-33ECA51AAE16}\"},{\"DocumentPath\":\"project.json\",\"FactoryId\":\"{60B41405-7549-4783-88DD-C084BCE062E7}\"},{\"DocumentPath\":\"Performer.xaml\",\"FactoryId\":\"{ACB8E7BA-F093-44C1-9B50-33ECA51AAE16}\"}]","ProjectBreakpoints":"{\"Value\":{\"Buoi7.xaml\":[{\"ConditionalExpression\":null,\"ActionExpression\":null,\"ExpectedHitCounter\":null,\"ShouldContinueAfterAction\":false,\"BreakpointType\":1,\"LocationIdentifier\":\"Log Message\",\"IsEnabled\":true,\"Annotation\":null,\"Id\":\"b90316bf-7ade-48fb-8c23-e3588fcd681c\",\"ActivityIdRef\":\"LogMessage_1\",\"ActivityId\":\"1.4\",\"ActivityName\":\"Log Message\",\"IsTransient\":false}],\"Performer.xaml\":[{\"ConditionalExpression\":null,\"ActionExpression\":null,\"ExpectedHitCounter\":null,\"ShouldContinueAfterAction\":false,\"BreakpointType\":1,\"LocationIdentifier\":\"Build Data Table\",\"IsEnabled\":true,\"Annotation\":null,\"Id\":\"bacf2b10-8580-4e26-bb01-07eff13d501f\",\"ActivityIdRef\":\"BuildDataTable_3\",\"ActivityId\":\"1.96\",\"ActivityName\":\"Build Data Table\",\"IsTransient\":false},{\"ConditionalExpression\":null,\"ActionExpression\":null,\"ExpectedHitCounter\":null,\"ShouldContinueAfterAction\":false,\"BreakpointType\":1,\"LocationIdentifier\":\"If\",\"IsEnabled\":true,\"Annotation\":null,\"Id\":\"14aa8657-2f3f-41d2-83b3-36bf62d83a83\",\"ActivityIdRef\":\"If_1\",\"ActivityId\":\"1.6\",\"ActivityName\":\"If\",\"IsTransient\":false}]},\"CodeBreakpoints\":{}}","ProjectWatches":"{\"Value\":[{\"Id\":\"e607ecdb-14f7-4b0d-9bd0-25afa5a3a4c9\",\"Expression\":\"page\",\"Type\":0},{\"Id\":\"b49eb125-a0ca-418d-b424-45f54a6b44f8\",\"Expression\":\"10/5\",\"Type\":0},{\"Id\":\"dc62e660-284c-425b-879b-6e5b09900f7c\",\"Expression\":\"ExtractDataTable\",\"Type\":0},{\"Id\":\"8d609dcc-3356-4047-9bc0-1b65734b30b8\",\"Expression\":\"dDate\",\"Type\":0},{\"Id\":\"5c0364c4-5478-4d03-a572-12431eaea126\",\"Expression\":\"Ki\",\"Type\":0},{\"Id\":\"243a4182-ef48-4dcb-a833-49193b69f1ea\",\"Expression\":\"CurrentRow(\\\"Bộ số\\\").ToString.Substring(0,2)\",\"Type\":0},{\"Id\":\"f3638bd7-d769-4291-a0d4-4fe56c07e41c\",\"Expression\":\"CurrentRow(\\\"Bộ số\\\").ToString\",\"Type\":0},{\"Id\":\"7b3f86e5-64c1-494b-b045-a31525f23b3d\",\"Expression\":\"CurrentRow(\\\"Bộ số\\\").ToString.Substring(14,2)\",\"Type\":0},{\"Id\":\"fabc55de-6a54-4a0b-9e9a-623c96ef0b3d\",\"Expression\":\"CurrentRow(\\\"Bộ số\\\").ToString.Substring(10,2)\",\"Type\":0},{\"Id\":\"8374e211-12e1-4270-87a4-822ee4cd9ddb\",\"Expression\":\"dtVietlot\",\"Type\":0},{\"Id\":\"4591be88-ebe1-49c3-831d-0fa6c363258d\",\"Expression\":\"Address\",\"Type\":0},{\"Id\":\"02d537af-103c-40ba-a536-aadd63d4c35a\",\"Expression\":\"aaaa\",\"Type\":0},{\"Id\":\"f1736c48-cb74-4de3-9bf7-86f6ded67599\",\"Expression\":\"rs\",\"Type\":0},{\"Id\":\"f7a8e03d-8bff-4381-b348-36e1611a5e38\",\"Expression\":\"orionMail.ToString\",\"Type\":0},{\"Id\":\"da6a26ce-2526-4459-ab03-9e1398275c4f\",\"Expression\":\"CurrentMail.Sender.ToString\",\"Type\":0},{\"Id\":\"eeb89a3d-3c2a-48e8-9b5b-77258d1a52bf\",\"Expression\":\"time\",\"Type\":0},{\"Id\":\"80ff45dc-b43a-43ff-bd43-bea0a3a4b61d\",\"Expression\":\"selectedTime\",\"Type\":0},{\"Id\":\"79c01933-ec41-4bab-a6f3-e265282e15da\",\"Expression\":\"CurrentMail.DateAsDateTime.Month.ToString\",\"Type\":0},{\"Id\":\"c3e1aef6-4cd1-44b1-ad49-366648e432ef\",\"Expression\":\"text\",\"Type\":0},{\"Id\":\"2f206f62-797a-4a64-b87e-0dbf91aec504\",\"Expression\":\"newStr\",\"Type\":0},{\"Id\":\"995ae649-fd0e-43cf-8573-166ea026c552\",\"Expression\":\"strBody\",\"Type\":0},{\"Id\":\"21cca01d-a664-459d-8ac3-f7054a96d94f\",\"Expression\":\"dtData\",\"Type\":0},{\"Id\":\"9a3d3d00-9b1a-4b9b-b877-89331ffea9dc\",\"Expression\":\"dtData(0)\",\"Type\":0},{\"Id\":\"7058ff05-7a19-4449-8e0f-12ff194a00c4\",\"Expression\":\"TransactionItem\",\"Type\":0},{\"Id\":\"492e5b9c-578f-44f0-8a6b-16b304f5d8b8\",\"Expression\":\"ExtractDataTable\",\"Type\":0},{\"Id\":\"68f015c0-7a27-414c-ab4f-6d50e769b39b\",\"Expression\":\"page\",\"Type\":0},{\"Id\":\"13055d4e-e580-4bb1-9a0d-eda0adf3c264\",\"Expression\":\"dtVietlot\",\"Type\":0}]}","LibraryProjectSettings":"{\"IncludeSourcesByDefault\":true,\"CompileExpressions\":true,\"ReadyToRun\":false,\"DefaultActivitiesRootCategories\":[null]}"}